bda/__init__.py
bda/bda_tools.py
bda/decorr_calc.py
bda-0.1.1.data/scripts/apply_bda.py
bda-0.1.1.dist-info/LICENSE
bda-0.1.1.dist-info/METADATA
bda-0.1.1.dist-info/WHEEL
bda-0.1.1.dist-info/top_level.txt
bda-0.1.1.dist-info/RECORD
