Metadata-Version: 2.1
Name: bda
Version: 0.1.1
Summary: a tool for applying baseline-dependent averaging to a radio interferometer dataset
Home-page: https://github.com/HERA-Team/baseline_dependent_averaging
Author: Paul La Plante
License: BSD
Keywords: baseline dependent averaging
Platform: UNKNOWN
Classifier: Development Status :: 4 - Beta
Classifier: Intended Audience :: Science/Research
Classifier: License :: OSI Approved :: BSD License
Classifier: Programming Language :: Python :: 3.6
Classifier: Programming Language :: Python :: 3.7
Classifier: Programming Language :: Python :: 3.8
Classifier: Programming Language :: Python :: 3.9
Classifier: Topic :: Scientific/Engineering :: Astronomy
License-File: LICENSE
Requires-Dist: pyuvdata (>=2.2.0)
Requires-Dist: astropy (>=3.0)
Requires-Dist: setuptools-scm
Provides-Extra: testing
Requires-Dist: pytest (>=6.0) ; extra == 'testing'
Requires-Dist: pytest-cov ; extra == 'testing'
Requires-Dist: pre-commit ; extra == 'testing'
